pines/__init__.py
pines/addict.py
pines/appdirs.py
pines/attribute_dict.py
pines/busy_dir.py
pines/bytesize.py
pines/cluster.py
pines/codex.py
pines/colors.py
pines/configure.py
pines/counter.py
pines/daskworker.py
pines/datagram.py
pines/egnyte.py
pines/file_util.py
pines/geoviz.py
pines/gpr.py
pines/hardware_info.py
pines/img.py
pines/ipy.py
pines/latin_hypercube.py
pines/logger.py
pines/multirunner.py
pines/mysql.py
pines/omx_convert.exe
pines/omx_cube_converter.py
pines/persist.py
pines/plot.py
pines/popup.py
pines/postgres.py
pines/private_pip.py
pines/qlog.py
pines/rate_limiter.py
pines/remote_import.py
pines/repeater.py
pines/smartread.py
pines/stats.py
pines/streamers.py
pines/styles.py
pines/summarize.py
pines/tar.py
pines/temporary.py
pines/timesize.py
pines/uid.py
pines/xdrive.py
pines/xhtml.py
pines/zipdir.py
pines/gpr/__init__.py
pines/gpr/multitarget.py
pines/gpr/scalers.py
pines/gpr/selectors.py
pines-2.94.dist-info/LICENSE
pines-2.94.dist-info/METADATA
pines-2.94.dist-info/WHEEL
pines-2.94.dist-info/entry_points.txt
pines-2.94.dist-info/top_level.txt
pines-2.94.dist-info/RECORD
