Metadata-Version: 2.1
Name: pines
Version: 2.94
Summary: A toolkit for various purposes
Home-page: https://github.com/jpn--/pines
Author: Jeffrey Newman
Author-email: jeff@newman.me
License: MIT
Keywords: reusable code
Platform: UNKNOWN
Classifier: Development Status :: 4 - Beta
Classifier: License :: OSI Approved :: MIT License
Classifier: Programming Language :: Python :: 3.6
Requires-Dist: distributed (>=1.17.1)
Requires-Dist: dask (>=0.15)
Requires-Dist: egnyte (>=0.5.3)
Requires-Dist: pandas (>=0.20.1)
Requires-Dist: dbf (>=0.96)
Requires-Dist: numpy (>=1.13.1)
Requires-Dist: scipy (>=0.19.0)
Requires-Dist: tables (>=3.4.2)
Requires-Dist: psycopg2
